setup.py
pymarshmallow/__init__.py
pymarshmallow/cli.py
pymarshmallow.egg-info/PKG-INFO
pymarshmallow.egg-info/SOURCES.txt
pymarshmallow.egg-info/dependency_links.txt
pymarshmallow.egg-info/requires.txt
pymarshmallow.egg-info/top_level.txt