Metadata-Version: 2.1
Name: pymarshmallow
Version: 1.2
Summary: A package which allows you to create your own command-line interface. A parody of click and click-shell.
Author: pymarshmallow
